cityjson2jsonfg/__init__.py
cityjson2jsonfg/cli.py
cityjson2jsonfg/convert.py
cityjson2jsonfg-1.2.dist-info/LICENSE
cityjson2jsonfg-1.2.dist-info/METADATA
cityjson2jsonfg-1.2.dist-info/WHEEL
cityjson2jsonfg-1.2.dist-info/entry_points.txt
cityjson2jsonfg-1.2.dist-info/top_level.txt
cityjson2jsonfg-1.2.dist-info/RECORD
