Metadata-Version: 2.1
Name: cityjson2jsonfg
Version: 1.2
Summary: Convert CityJSON files to JSON-FG format
Author-email: 3DGI <info@3dgi.nl>
License: Apache-2.0 License
Project-URL: github, https://github.com/3DGI/cityjson2jsonfg
Classifier: Programming Language :: Python :: 3
Classifier: Topic :: Scientific/Engineering :: GIS
Classifier: License :: OSI Approved :: Apache Software License
Requires-Python: >=3.8
License-File: LICENSE
Requires-Dist: cjio ==0.8.2
Requires-Dist: click >=8.1
Requires-Dist: pyproj >=3.1
Provides-Extra: develop
Requires-Dist: pytest ; extra == 'develop'
Requires-Dist: tox ; extra == 'develop'
